<?xml version="1.0" encoding="UTF-8" standalone="no"?><root><prod id="1"><cprod>01</cprod><xprod>Arroz 5Kg</xprod><qcom>10</qcom><vuncom>13</vuncom><vprod>1300</vprod></prod><prod id="2"><cprod>02</cprod><xprod>Feijão 1Kg</xprod><qcom>10</qcom><vuncom>5</vuncom><vprod>500</vprod></prod><prod id="3"><cprod>03</cprod><xprod>Farinha de Trigo 1Kg</xprod><qcom>10</qcom><vuncom>2</vuncom><vprod>200</vprod></prod><prod id="4"><cprod>04</cprod><xprod>Extrato de Tomate 340g</xprod><qcom>10</qcom><vuncom>3</vuncom><vprod>300</vprod></prod><prod id="5"><cprod>05</cprod><xprod>Macarrão 500g</xprod><qcom>10</qcom><vuncom>1</vuncom><vprod>100</vprod></prod><prod id="6"><cprod>06</cprod><xprod>Biscoito Recheado 90g</xprod><qcom>10</qcom><vuncom>1</vuncom><vprod>100</vprod></prod><prod id="7"><cprod>07</cprod><xprod>Sardinha 125g</xprod><qcom>10</qcom><vuncom>3</vuncom><vprod>300</vprod></prod><prod id="8"><cprod>08</cprod><xprod>Café 500g</xprod><qcom>10</qcom><vuncom>7</vuncom><vprod>700</vprod></prod><prod id="9"><cprod>09</cprod><xprod>Salsinha Kg</xprod><qcom>10</qcom><vuncom>4</vuncom><vprod>400</vprod></prod><prod id="10"><cprod>10</cprod><xprod>Achocolatado em pó 800g</xprod><qcom>10</qcom><vuncom>9</vuncom><vprod>900</vprod></prod><prod id="11"><cprod>11</cprod><xprod>Gelatina 35g</xprod><qcom>10</qcom><vuncom>1</vuncom><vprod>100</vprod></prod><prod id="12"><cprod>12</cprod><xprod>Sabão em pó 1Kg</xprod><qcom>10</qcom><vuncom>6</vuncom><vprod>600</vprod></prod><prod id="13"><cprod>13</cprod><xprod>Sabonete 90g</xprod><qcom>10</qcom><vuncom>1</vuncom><vprod>100</vprod></prod><prod id="14"><cprod>14</cprod><xprod>Macarrão Instantaneo 90g</xprod><qcom>10</qcom><vuncom>2</vuncom><vprod>200</vprod></prod><prod id="15"><cprod>15</cprod><xprod>Adocante 100ml</xprod><qcom>10</qcom><vuncom>2</vuncom><vprod>200</vprod></prod><prod id="16"><cprod>16</cprod><xprod>Tomate Kg</xprod><qcom>10</qcom><vuncom>4</vuncom><vprod>400</vprod></prod><prod id="17"><cprod>17</cprod><xprod>Cenoura Kg</xprod><qcom>10</qcom><vuncom>3</vuncom><vprod>300</vprod></prod><prod id="18"><cprod>18</cprod><xprod>Pepino Kg</xprod><qcom>10</qcom><vuncom>1</vuncom><vprod>100</vprod></prod><prod id="19"><cprod>19</cprod><xprod>Chuchu Kg</xprod><qcom>10</qcom><vuncom>2</vuncom><vprod>200</vprod></prod><prod id="20"><cprod>20</cprod><xprod>Salgado Un</xprod><qcom>10</qcom><vuncom>2</vuncom><vprod>200</vprod></prod><prod id="21"><cprod>21</cprod><xprod>Berinjela Kg</xprod><qcom>10</qcom><vuncom>4</vuncom><vprod>400</vprod></prod><prod id="22"><cprod>22</cprod><xprod>Coca-Cola 2l</xprod><qcom>10</qcom><vuncom>5</vuncom><vprod>500</vprod></prod><prod id="23"><cprod>23</cprod><xprod>Creme dental 90g</xprod><qcom>10</qcom><vuncom>3</vuncom><vprod>300</vprod></prod><prod id="24"><cprod>24</cprod><xprod>Cerveja 350ml</xprod><qcom>10</qcom><vuncom>2</vuncom><vprod>200</vprod></prod><prod id="25"><cprod>25</cprod><xprod>Picanha Kg</xprod><qcom>10</qcom><vuncom>31</vuncom><vprod>3100</vprod></prod><prod id="26"><cprod>26</cprod><xprod>Cupim Kg</xprod><qcom>10</qcom><vuncom>22</vuncom><vprod>2200</vprod></prod><prod id="27"><cprod>27</cprod><xprod>Celular</xprod><qcom>10</qcom><vuncom>799</vuncom><vprod>79900</vprod></prod><prod id="28"><cprod>28</cprod><xprod>Notebook</xprod><qcom>10</qcom><vuncom>2199</vuncom><vprod>219900</vprod></prod><prod id="29"><cprod>29</cprod><xprod>Televisor 29</xprod><qcom>10</qcom><vuncom>1590</vuncom><vprod>159000</vprod></prod><prod id="30"><cprod>30</cprod><xprod>Vodka 900ml</xprod><qcom>10</qcom><vuncom>12</vuncom><vprod>1200</vprod></prod></root>